cortex/__init__.py
cortex/acquisition/__init__.py
cortex/acquisition/_graph_nei.py
cortex/assets/__init__.py
cortex/assets/protein_seq_tokenizer_32/__init__.py
cortex/assets/protein_seq_tokenizer_32/special_tokens_map.json
cortex/assets/protein_seq_tokenizer_32/tokenizer_config.json
cortex/assets/protein_seq_tokenizer_32/vocab.txt
cortex/attribution/__init__.py
cortex/attribution/_occlusion.py
cortex/cmdline/__init__.py
cortex/cmdline/benchmark_cortex_optimizer.py
cortex/cmdline/optimize_sequences.py
cortex/cmdline/train_cortex_model.py
cortex/config/__init__.py
cortex/config/hydra/__init__.py
cortex/config/hydra/optimize_proteins.yaml
cortex/config/hydra/train_protein_model.yaml
cortex/config/hydra/branches/generation.yaml
cortex/config/hydra/branches/protein_property.yaml
cortex/config/hydra/general_settings/default.yaml
cortex/config/hydra/logging/default.yaml
cortex/config/hydra/model_globals/default.yaml
cortex/config/hydra/roots/protein_seq.yaml
cortex/config/hydra/tasks/generation/gfp.yaml
cortex/config/hydra/tasks/protein_property/delta_g.yaml
cortex/config/hydra/tasks/protein_property/log_fluorescence.yaml
cortex/config/hydra/tasks/protein_property/stability.yaml
cortex/config/hydra/tree/protein_model.yaml
cortex/config/hydra/trunk/default.yaml
cortex/config/wandb/protein_model_sweep.yaml
cortex/constants/__init__.py
cortex/constants/_protein_constants.py
cortex/corruption/__init__.py
cortex/corruption/_abstract_corruption.py
cortex/corruption/_diffusion_noise_schedule.py
cortex/corruption/_gaussian_corruption.py
cortex/corruption/_mask_corruption.py
cortex/data/__init__.py
cortex/data/data_module/__init__.py
cortex/data/data_module/_task_data_module.py
cortex/data/dataset/__init__.py
cortex/data/dataset/_data_frame_dataset.py
cortex/data/dataset/_numpy_dataset.py
cortex/data/dataset/_rfp_dataset.py
cortex/data/dataset/_tape_fluorescence.py
cortex/data/dataset/_tape_stability.py
cortex/data/dataset/_transformed_dataset.py
cortex/data/samplers/__init__.py
pytorch_cortex-0.0.4.dist-info/LICENSE
pytorch_cortex-0.0.4.dist-info/METADATA
pytorch_cortex-0.0.4.dist-info/WHEEL
pytorch_cortex-0.0.4.dist-info/entry_points.txt
pytorch_cortex-0.0.4.dist-info/top_level.txt
pytorch_cortex-0.0.4.dist-info/RECORD
