Metadata-Version: 2.1
Name: pytorch-cortex
Version: 0.0.4
Summary: A modular architecture for deep learning systems.
Author-email: Samuel Stanton <stanton.samuel@gene.com>
Classifier: Development Status :: 3 - Alpha
Classifier: Intended Audience :: Science/Research
Classifier: Programming Language :: Python :: 3
License-File: LICENSE
Requires-Dist: torch
Requires-Dist: torchvision
Requires-Dist: pytorch-warmup
Requires-Dist: botorch >=0.9.4
Requires-Dist: wandb
Requires-Dist: tabulate
Requires-Dist: omegaconf
Requires-Dist: hydra-core >=1.2.0
Requires-Dist: tqdm
Requires-Dist: pandas
Requires-Dist: cachetools
Requires-Dist: edlib
Requires-Dist: transformers
Requires-Dist: lightning ==1.9.5
Requires-Dist: pytorch-lightning ==1.9.5
Requires-Dist: universal-pathlib
Requires-Dist: pyarrow
Requires-Dist: s3fs
Provides-Extra: dev
Requires-Dist: pytest ; extra == 'dev'
Requires-Dist: pip-tools ; extra == 'dev'
Requires-Dist: pytest-cov ; extra == 'dev'
Requires-Dist: pre-commit ; extra == 'dev'
Requires-Dist: sphinx ; extra == 'dev'
Requires-Dist: sphinx-rtd-theme ; extra == 'dev'
Requires-Dist: sphinx-autoapi ; extra == 'dev'
